complychain/__init__.py
complychain/__main__.py
complychain/audit_server.py
complychain/audit_system.py
complychain/cli.py
complychain/cli_enhanced.py
complychain/crypto_engine.py
complychain/py.typed
complychain/threat_scanner.py
complychain/compliance/glba_engine.py
complychain/config/__init__.py
complychain/config/logging_config.py
complychain/detection/__init__.py
complychain/detection/ml_engine.py
complychain/exceptions/__init__.py
complychain/tests/__init__.py
complychain/tests/test_audit.py
complychain/tests/test_compliance.py
complychain/tests/test_scanner.py
complychain/tests/cli/test_cli_usage.py
complychain-1.0.0.dist-info/licenses/LICENSE
complychain-1.0.0.dist-info/METADATA
complychain-1.0.0.dist-info/WHEEL
complychain-1.0.0.dist-info/entry_points.txt
complychain-1.0.0.dist-info/top_level.txt
complychain-1.0.0.dist-info/RECORD
