Metadata-Version: 2.4
Name: complychain
Version: 1.0.0
Summary: Enterprise-grade GLBA compliance toolkit with quantum-safe cryptography
Home-page: https://github.com/RanaEhtashamAli/comply-chain
Author: Rana Ehtasham Ali
Author-email: Rana Ehtasham Ali <ranaehtashamali1@gmail.com>
Maintainer-email: Rana Ehtasham Ali <ranaehtashamali1@gmail.com>
License: Apache-2.0
Project-URL: Homepage, https://github.com/RanaEhtashamAli/comply-chain
Project-URL: Documentation, https://complychain.readthedocs.io
Project-URL: Repository, https://github.com/RanaEhtashamAli/comply-chain
Project-URL: Bug Tracker, https://github.com/RanaEhtashamAli/comply-chain/issues
Project-URL: Security Policy, https://github.com/RanaEhtashamAli/comply-chain/security/policy
Project-URL: Release Notes, https://github.com/RanaEhtashamAli/comply-chain/releases
Project-URL: Funding, https://github.com/sponsors/RanaEhtashamAli
Keywords: glba,compliance,cryptography,quantum-safe,audit,fintech,regtech
Classifier: Development Status :: 5 - Production/Stable
Classifier: Intended Audience :: Financial and Insurance Industry
Classifier: Intended Audience :: Developers
Classifier: Intended Audience :: System Administrators
Classifier: Topic :: Security :: Cryptography
Classifier: Topic :: Office/Business :: Financial
Classifier: Topic :: Software Development :: Libraries :: Python Modules
Classifier: License :: OSI Approved :: Apache Software License
Classifier: Programming Language :: Python :: 3
Classifier: Programming Language :: Python :: 3.9
Classifier: Programming Language :: Python :: 3.10
Classifier: Programming Language :: Python :: 3.11
Classifier: Programming Language :: Python :: 3.12
Classifier: Operating System :: OS Independent
Classifier: Operating System :: Microsoft :: Windows
Classifier: Operating System :: POSIX :: Linux
Classifier: Operating System :: MacOS
Classifier: Environment :: Console
Classifier: Framework :: Pytest
Classifier: Typing :: Typed
Requires-Python: >=3.9
License-File: LICENSE
Requires-Dist: scikit-learn>=1.3.0
Requires-Dist: reportlab>=4.0.0
Requires-Dist: click>=8.0.0
Requires-Dist: cryptography>=41.0.0
Requires-Dist: joblib>=1.3.0
Requires-Dist: numpy>=1.24.0
Requires-Dist: requests>=2.31.0
Requires-Dist: pyyaml>=6.0.0
Requires-Dist: typer>=0.9.0
Requires-Dist: rich>=13.0.0
Requires-Dist: pqcrypto<0.4.0,>=0.3.4
Requires-Dist: PyPDF2>=3.0.0
Provides-Extra: quantum
Provides-Extra: pqcrypto
Requires-Dist: pqcrypto>=0.3.0; extra == "pqcrypto"
Provides-Extra: legacy
Requires-Dist: pqcrypto>=0.3.0; extra == "legacy"
Provides-Extra: dev
Requires-Dist: pytest>=7.0.0; extra == "dev"
Requires-Dist: pytest-cov>=4.0.0; extra == "dev"
Requires-Dist: pytest-mock>=3.10.0; extra == "dev"
Requires-Dist: black>=23.0.0; extra == "dev"
Requires-Dist: ruff>=0.1.0; extra == "dev"
Requires-Dist: mypy>=1.0.0; extra == "dev"
Requires-Dist: coverage-badge>=1.1.0; extra == "dev"
Provides-Extra: test
Requires-Dist: pytest>=7.0.0; extra == "test"
Requires-Dist: pytest-cov>=4.0.0; extra == "test"
Requires-Dist: pytest-mock>=3.10.0; extra == "test"
Provides-Extra: docs
Requires-Dist: sphinx>=6.0.0; extra == "docs"
Requires-Dist: sphinx-rtd-theme>=1.2.0; extra == "docs"
Dynamic: author
Dynamic: home-page
Dynamic: license-file
Dynamic: requires-python
